README.md
setup.py
conan_deploy_tool/__init__.py
conan_deploy_tool/conan.png
conan_deploy_tool/conan_deploy_tool.py
conan_deploy_tool/main.py
conan_deploy_tool/requirements.txt
conan_deploy_tool/requirements_test.txt
conan_deploy_tool.egg-info/PKG-INFO
conan_deploy_tool.egg-info/SOURCES.txt
conan_deploy_tool.egg-info/dependency_links.txt
conan_deploy_tool.egg-info/entry_points.txt
conan_deploy_tool.egg-info/requires.txt
conan_deploy_tool.egg-info/top_level.txt