Metadata-Version: 2.1
Name: conan-deploy-tool
Version: 0.0.2
Summary: script to deploy conan-based applications
Home-page: https://github.com/SSE4/conan-deploy-tool
Author: Bincrafters
Author-email: bincrafters@gmail.com
License: MIT
Keywords: conan,C/C++,package,libraries,developer,manager,dependency,tool,c,c++,cpp
Platform: UNKNOWN
Classifier: Development Status :: 4 - Beta
Classifier: Intended Audience :: Developers
Classifier: Topic :: Software Development :: Build Tools
Classifier: License :: OSI Approved :: MIT License
Classifier: Programming Language :: Python :: 2
Classifier: Programming Language :: Python :: 2.7
Classifier: Programming Language :: Python :: 3
Classifier: Programming Language :: Python :: 3.6
Provides-Extra: test
